{
   "lang":"fr",
   "sites":[
      {
         "siteName":"Service-Public.fr",
         "siteUrls":[
            "https://www.service-public.fr/",
            "https://www.service-public.fr/P10017",
            "https://www.service-public.fr/particuliers/actualites/A14434",
            "https://www.service-public.fr/particuliers/vosdroits/F12242"
         ]
      },
      {
         "siteName":"impots.gouv.fr",
         "siteUrls":[
            "https://www.impots.gouv.fr/accueil",
            "https://www.impots.gouv.fr/contacts",
            "https://www.impots.gouv.fr/actualite/transfert-la-dgfip-du-recouvrement-de-laccise-sur-les-tabacs-et-les-alcools-depuis-le-1er",
            "https://www.impots.gouv.fr/particulier/declarer-mes-revenus"
         ]
      },
      {
         "siteName":"Leboncoin",
         "siteUrls":[
            "https://www.leboncoin.fr/",
            "https://www.leboncoin.fr/_immobilier_/offres",
            "https://www.leboncoin.fr/deposer-une-annonce",
            "https://www.leboncoin.fr/boutique/11532/postulez_aux_offres_d_emploi_leboncoin.htm"
         ]
      },
      {
         "siteName":"SNCF Connect",
         "siteUrls":[
            "https://www.sncf-connect.com/",
            "https://www.sncf-connect.com/aide/contact",
            "https://www.sncf-connect.com/app/catalogue",
            "https://www.sncf-connect.com/app/trips"
         ]
      }
   ]
}